LICENSE.txt
MANIFEST.in
README.rst
check_es_cluster_status.py
check_es_jvm_usage.py
check_es_nodes.py
check_es_split_brain.py
check_es_unassigned_shards.py
requirements.txt
setup.cfg
setup.py
nagios_elasticsearch.egg-info/PKG-INFO
nagios_elasticsearch.egg-info/SOURCES.txt
nagios_elasticsearch.egg-info/dependency_links.txt
nagios_elasticsearch.egg-info/requires.txt
nagios_elasticsearch.egg-info/top_level.txt