Metadata-Version: 1.1
Name: nagios-elasticsearch
Version: 0.1.2
Summary: A selection of Nagios plugins to monitor ElasticSearch.
Home-page: https://github.com/opentable/nagios-elasticsearch
Author: Paul Stack
Author-email: public@paulstack.co.uk
License: MIT
Download-URL: https://github.com/stack72/nagios-elasticsearch/tarball/0.1.2
Keywords: monitoring,nagios,elasticsearch
Platform: UNKNOWN
